README.rst
setup.py
test/test_fields.py
test/test_pass.py
test/test_template.py
test/test_util.py
uareach/__about__.py
uareach/__init__.py
uareach/common.py
uareach/core.py
uareach/fields.py
uareach/passes.py
uareach/projects.py
uareach/templates.py
uareach/util.py
uareach.egg-info/PKG-INFO
uareach.egg-info/SOURCES.txt
uareach.egg-info/dependency_links.txt
uareach.egg-info/requires.txt
uareach.egg-info/top_level.txt