Metadata-Version: 1.1
Name: uareach
Version: 0.1.1
Summary: Python package for using the Airship Wallet API
Home-page: https://airship.com/
Author: Airship Customer Engineering
Author-email: customer-engineering@airship.com
License: BSD License
Platform: UNKNOWN
Classifier: Development Status :: 4 - Beta
Classifier: Environment :: Web Environment
Classifier: Intended Audience :: Developers
Classifier: License :: OSI Approved :: Apache Software License
Classifier: Operating System :: OS Independent
Classifier: Topic :: Software Development :: Libraries
